panik/__init__.py
panik-1.0.0.dist-info/LICENSE
panik-1.0.0.dist-info/METADATA
panik-1.0.0.dist-info/WHEEL
panik-1.0.0.dist-info/top_level.txt
panik-1.0.0.dist-info/RECORD
