Metadata-Version: 2.1
Name: panik
Version: 1.0.0
Summary: Will change problem into panik
Home-page: https://github.com/tomsimonart/panik
Author: Tom Simonart
Author-email: tom.simonart@gmail.com
License: UNKNOWN
Platform: UNKNOWN
Classifier: Programming Language :: Python :: 3
Classifier: Development Status :: 5 - Production/Stable
Classifier: License :: OSI Approved :: MIT License
Classifier: Operating System :: OS Independent
Classifier: Topic :: Utilities
Requires-Python: >=3.0
